reader/__init__.py
reader/__main__.py
reader/feed.py
helper_flask_jwt-1.7.0.dist-info/LICENSE
helper_flask_jwt-1.7.0.dist-info/METADATA
helper_flask_jwt-1.7.0.dist-info/WHEEL
helper_flask_jwt-1.7.0.dist-info/entry_points.txt
helper_flask_jwt-1.7.0.dist-info/top_level.txt
helper_flask_jwt-1.7.0.dist-info/RECORD
