Metadata-Version: 2.1
Name: helper-flask-jwt
Version: 1.7.0
Summary: Library to implement jwt in flassk
Author-email: achu <achu@GMAIL.com>
License: MIT License
Project-URL: repository, https://github.com/achu/reader
Project-URL: documentation, https://tinyurl.com/achu
Keywords: feed,reader,tutorial
Classifier: License :: OSI Approved :: MIT License
Classifier: Programming Language :: Python
Classifier: Programming Language :: Python :: 3
Requires-Python: >=3.5
License-File: LICENSE
Provides-Extra: build
Requires-Dist: build ; extra == 'build'
Requires-Dist: twine ; extra == 'build'
Provides-Extra: dev
Requires-Dist: black ; extra == 'dev'
Requires-Dist: bumpver ; extra == 'dev'
Requires-Dist: isort ; extra == 'dev'
Requires-Dist: mypy ; extra == 'dev'
Requires-Dist: pytest ; extra == 'dev'
